odoo8_addon_partner_helper-8.0.0.1.0.99.dev7-py2.7-nspkg.pth
odoo8_addon_partner_helper-8.0.0.1.0.99.dev7.dist-info/DESCRIPTION.rst
odoo8_addon_partner_helper-8.0.0.1.0.99.dev7.dist-info/METADATA
odoo8_addon_partner_helper-8.0.0.1.0.99.dev7.dist-info/RECORD
odoo8_addon_partner_helper-8.0.0.1.0.99.dev7.dist-info/WHEEL
odoo8_addon_partner_helper-8.0.0.1.0.99.dev7.dist-info/metadata.json
odoo8_addon_partner_helper-8.0.0.1.0.99.dev7.dist-info/namespace_packages.txt
odoo8_addon_partner_helper-8.0.0.1.0.99.dev7.dist-info/top_level.txt
odoo_addons/partner_helper/__init__.py
odoo_addons/partner_helper/__openerp__.py
odoo_addons/partner_helper/partner.py
odoo_addons/partner_helper/i18n/de.po
odoo_addons/partner_helper/i18n/es.po
odoo_addons/partner_helper/i18n/eu.po
odoo_addons/partner_helper/i18n/fi.po
odoo_addons/partner_helper/i18n/it.po
odoo_addons/partner_helper/i18n/nl.po
odoo_addons/partner_helper/i18n/partner_helper.pot
odoo_addons/partner_helper/i18n/pt_BR.po
odoo_addons/partner_helper/i18n/sl.po
odoo_addons/partner_helper/static/description/icon.png
